dt_extra_sdk/__init__.py
dt_extra_sdk/entry/__init__.py
dt_extra_sdk/module/__init__.py
dt_extra_sdk/module/connector.py
dt_extra_sdk/module/error.py
dt_extra_sdk/module/kit.py
dt_extra_sdk/module/model.py
dt_extra_sdk-0.0.5.dist-info/METADATA
dt_extra_sdk-0.0.5.dist-info/WHEEL
dt_extra_sdk-0.0.5.dist-info/top_level.txt
dt_extra_sdk-0.0.5.dist-info/RECORD
